docker_sign_verify/__init__.py
docker_sign_verify/exceptions.py
docker_sign_verify/gpgsigner.py
docker_sign_verify/imageconfig.py
docker_sign_verify/pkisigner.py
docker_sign_verify/registryv2.py
docker_sign_verify/registryv2manifest.py
docker_sign_verify/registryv2manifestlist.py
docker_sign_verify/signer.py
docker_sign_verify/specs.py
docker_sign_verify/utils.py
docker_sign_verify/scripts/__init__.py
docker_sign_verify/scripts/dsv.py
docker_sign_verify/scripts/utils.py
tests/__init__.py
tests/conftest.py
tests/stubs.py
tests/test_gpgsigner.py
tests/test_imageconfig.py
tests/test_pkisigner.py
tests/test_registryv2.py
tests/test_registryv2_proxy.py
tests/test_registryv2manifest.py
tests/test_registryv2manifestlist.py
tests/test_scripts_dsv.py
tests/testutils.py
docker_sign_verify-2.1.0.dist-info/LICENSE.md
docker_sign_verify-2.1.0.dist-info/METADATA
docker_sign_verify-2.1.0.dist-info/WHEEL
docker_sign_verify-2.1.0.dist-info/entry_points.txt
docker_sign_verify-2.1.0.dist-info/top_level.txt
docker_sign_verify-2.1.0.dist-info/RECORD
