Metadata-Version: 2.1
Name: docker-sign-verify
Version: 2.1.0
Summary: A utility that can be used to sign and verify docker images.
Home-page: https://github.com/crashvb/docker-sign-verify
Author: Richard Davis
Author-email: crashvb@gmail.com
License: Apache License 2.0
Project-URL: Bug Reports, https://github.com/crashvb/docker-sign-verify/issues
Project-URL: Source, https://github.com/crashvb/docker-sign-verify
Keywords: docker docker-sign docker-verify integrity sign signatures verify
Platform: UNKNOWN
Classifier: Development Status :: 5 - Production/Stable
Classifier: Intended Audience :: Developers
Classifier: License :: OSI Approved :: Apache Software License
Classifier: Programming Language :: Python :: 3
Classifier: Programming Language :: Python :: 3.8
Classifier: Programming Language :: Python :: 3.9
Classifier: Programming Language :: Python :: 3.10
Classifier: Operating System :: OS Independent
License-File: LICENSE.md
Requires-Dist: aiofiles<23.2.0
Requires-Dist: aiohttp
Requires-Dist: aiotempfile
Requires-Dist: canonicaljson
Requires-Dist: docker-registry-client-async>=0.2.3
Requires-Dist: click
Requires-Dist: pycryptodome
Provides-Extra: dev
Requires-Dist: black; extra == "dev"
Requires-Dist: coveralls; extra == "dev"
Requires-Dist: docker; extra == "dev"
Requires-Dist: lovely-pytest-docker; extra == "dev"
Requires-Dist: pylint; extra == "dev"
Requires-Dist: pytest; extra == "dev"
Requires-Dist: pytest-asyncio; extra == "dev"
Requires-Dist: pytest-cov; extra == "dev"
Requires-Dist: pytest-docker-registry-fixtures; extra == "dev"
Requires-Dist: pytest-docker-squid-fixtures>=0.1.2; extra == "dev"
Requires-Dist: pytest-gnupg-fixtures; extra == "dev"
Requires-Dist: pytest-select; extra == "dev"
Requires-Dist: twine; extra == "dev"
Requires-Dist: wheel; extra == "dev"
